areaparam/__init__.py
areaparam/circle.py
areaparam/rectangle.py
areaparam/square.py
areaparam-0.1.0.dist-info/licenses/LICENSE
areaparam-0.1.0.dist-info/METADATA
areaparam-0.1.0.dist-info/WHEEL
areaparam-0.1.0.dist-info/top_level.txt
areaparam-0.1.0.dist-info/RECORD
